databathing/__init__.py
databathing/pipeline.py
databathing/py_bathing.py
databathing/v1.py
databathing/auto_selection/__init__.py
databathing/auto_selection/data_estimator.py
databathing/auto_selection/engine_selector.py
databathing/auto_selection/query_analyzer.py
databathing/auto_selection/rule_engine.py
databathing/engines/__init__.py
databathing/engines/base_engine.py
databathing/engines/duckdb_engine.py
databathing/engines/mojo_engine.py
databathing/engines/spark_engine.py
databathing/validation/__init__.py
databathing/validation/async_validator.py
databathing/validation/code_validator.py
databathing/validation/custom_rules.py
databathing/validation/duckdb_validator.py
databathing/validation/spark_validator.py
databathing/validation/validation_cache.py
databathing/validation/validation_report.py
databathing/validation/validator_factory.py
databathing-0.9.1.dist-info/licenses/LICENSE
tests/__init__.py
tests/test_auto_selection.py
tests/test_cte_with_joins.py
tests/test_distinct.py
tests/test_duckdb_engine.py
tests/test_groupby_having.py
tests/test_join_on.py
tests/test_mojo_engine.py
tests/test_orderby.py
tests/test_select_from_where.py
tests/test_set_operations.py
tests/test_split.py
tests/test_struct.py
tests/test_validation_system.py
tests/test_windows.py
tests/test_with.py
databathing-0.9.1.dist-info/METADATA
databathing-0.9.1.dist-info/WHEEL
databathing-0.9.1.dist-info/top_level.txt
databathing-0.9.1.dist-info/RECORD
