Metadata-Version: 2.4
Name: databathing
Version: 0.9.1
Summary: Advanced SQL-to-code generator with intelligent auto-selection, multi-engine support, validation, and performance optimization
Home-page: https://github.com/jason-jz-zhu/databathing
Author: Jiazhen Zhu, Sanhe Hu
Author-email: jason.jz.zhu@gmail.com, husanhe@email.com
Maintainer: Jiazhen Zhu
Maintainer-email: jason.jz.zhu@gmail.com
License: MIT
Project-URL: Homepage, https://github.com/jason-jz-zhu/databathing
Project-URL: Bug Tracker, https://github.com/jason-jz-zhu/databathing/issues
Project-URL: Source Code, https://github.com/jason-jz-zhu/databathing
Keywords: sql,spark,pyspark,duckdb,etl,data,parser,converter,validation,quality,auto-selection,intelligent,optimization
Classifier: Development Status :: 3 - Alpha
Classifier: Topic :: Software Development :: Libraries
Classifier: Topic :: Software Development :: Libraries :: Python Modules
Classifier: Topic :: Database
Classifier: Topic :: Scientific/Engineering
Classifier: Programming Language :: SQL
Classifier: Programming Language :: Python :: 3.7
Classifier: Programming Language :: Python :: 3.8
Classifier: Programming Language :: Python :: 3.9
Classifier: Programming Language :: Python :: 3.10
Classifier: Programming Language :: Python :: 3.11
Classifier: License :: OSI Approved :: MIT License
Requires-Python: >=3.7
License-File: LICENSE
Requires-Dist: mo-sql-parsing
Provides-Extra: dev
Requires-Dist: pytest; extra == "dev"
Requires-Dist: pytest-cov; extra == "dev"
Provides-Extra: test
Requires-Dist: pytest; extra == "test"
Requires-Dist: pytest-cov; extra == "test"
Provides-Extra: validation
Requires-Dist: sqlparse>=0.4.0; extra == "validation"
Provides-Extra: duckdb
Requires-Dist: duckdb; extra == "duckdb"
Provides-Extra: all
Requires-Dist: sqlparse>=0.4.0; extra == "all"
Requires-Dist: duckdb; extra == "all"
Dynamic: author
Dynamic: author-email
Dynamic: classifier
Dynamic: description
Dynamic: description-content-type
Dynamic: home-page
Dynamic: keywords
Dynamic: license
Dynamic: license-file
Dynamic: maintainer
Dynamic: maintainer-email
Dynamic: project-url
Dynamic: provides-extra
Dynamic: requires-dist
Dynamic: requires-python
Dynamic: summary
